{
  "nextId": 17,
  "accounts": [
    {
      "id": 1,
      "name": "Ellen Souza",
      "balance": 300000
    },
    {
      "id": 2,
      "name": "Renato Augusto Souza",
      "balance": 50000
    },
    {
      "id": 3,
      "name": "Henrique Manata",
      "balance": 3000
    },
    {
      "id": 5,
      "name": "Hélio Souza",
      "balance": 30000000
    },
    {
      "id": 6,
      "name": "Eloá Souza Silva",
      "balance": 30000000
    },
    {
      "id": 7,
      "name": "Marco Souza Silva",
      "balance": 30000000
    },
    {
      "id": 8,
      "name": "Marco Souza Silva",
      "balance": 30000000
    },
    {
      "id": 9,
      "name": "Marco Souza Silva",
      "balance": 30000000
    },
    {
      "id": 10,
      "name": "Marco Souza Silva",
      "balance": 30000000
    },
    {
      "id": 11,
      "name": "Marco Souza Silva",
      "balance": 30000000
    },
    {
      "id": 12,
      "name": "Marco Souza Silva",
      "balance": 30000000
    },
    {
      "id": 13,
      "name": "Marco Souza Silva",
      "balance": 30000000
    },
    {
      "id": 14,
      "name": "Marco Souza Silva",
      "balance": 30000000
    },
    {
      "id": 15,
      "name": "Marco Souza Silva",
      "balance": 30000000
    },
    {
      "id": 16,
      "name": "Marco Souza Silva",
      "balance": 30000000
    }
  ]
}